odoo/addons/pos_reset_search/README.rst
odoo/addons/pos_reset_search/__init__.py
odoo/addons/pos_reset_search/__manifest__.py
odoo/addons/pos_reset_search/i18n/es.po
odoo/addons/pos_reset_search/i18n/it.po
odoo/addons/pos_reset_search/i18n/pos_reset_search.pot
odoo/addons/pos_reset_search/readme/CONTRIBUTORS.rst
odoo/addons/pos_reset_search/readme/DESCRIPTION.rst
odoo/addons/pos_reset_search/readme/USAGE.rst
odoo/addons/pos_reset_search/static/description/icon.png
odoo/addons/pos_reset_search/static/description/index.html
odoo/addons/pos_reset_search/static/src/js/Screens/ProductScreen/ProductScreen.js
odoo/addons/pos_reset_search/static/src/js/Screens/ProductScreen/ControlButtons/ProductsWidgetControlPanel.esm.js
odoo_addon_pos_reset_search-16.0.1.0.0.5.dist-info/METADATA
odoo_addon_pos_reset_search-16.0.1.0.0.5.dist-info/WHEEL
odoo_addon_pos_reset_search-16.0.1.0.0.5.dist-info/top_level.txt
odoo_addon_pos_reset_search-16.0.1.0.0.5.dist-info/RECORD
